gendc_python/__init__.py
gendc_python/version.py
gendc_python/gendc_separator/__init__.py
gendc_python/gendc_separator/component.py
gendc_python/gendc_separator/descriptor.py
gendc_python/gendc_separator/part.py
gendc_python/gendc_separator/utils.py
gendc_python/genicam/__init__.py
gendc_python/genicam/pfnc_mapping.py
gendc_python/genicam/sfnc_values.py
gendc_python/genicam/tool.py
gendc_python-0.4.1.dist-info/LICENSE.txt
gendc_python-0.4.1.dist-info/METADATA
gendc_python-0.4.1.dist-info/WHEEL
gendc_python-0.4.1.dist-info/top_level.txt
gendc_python-0.4.1.dist-info/RECORD
